_pylumi.cpython-36m-darwin.h
_pylumi.cpython-36m-darwin.so
pylumi/__init__.py
pylumi/context.py
pylumi/exc.py
pylumi/ext.py
pylumi/provider.py
pylumi/urn.py
pylumi-1.3.0.dist-info/LICENSE.md
pylumi-1.3.0.dist-info/METADATA
pylumi-1.3.0.dist-info/WHEEL
pylumi-1.3.0.dist-info/top_level.txt
pylumi-1.3.0.dist-info/RECORD
