Metadata-Version: 2.1
Name: pylumi
Version: 1.3.0
Summary: Python API for interacting with Pulumi resource plugins.
Home-page: https://github.com/cfeenstra67/pylumi
Author: Cam Feenstra
Author-email: cameron.l.feenstra@gmail.com
License: MIT
Keywords: go cython terraform pulumi infra-as-code cloudformation
Platform: UNKNOWN
Classifier: Development Status :: 1 - Planning
Classifier: Programming Language :: Cython
Classifier: Programming Language :: Python :: 3
Classifier: License :: OSI Approved :: MIT License
Requires-Dist: dataclasses (==0.7) ; python_version < "3.7"
Provides-Extra: dev
Requires-Dist: cython ; extra == 'dev'
Requires-Dist: twine ; extra == 'dev'
Requires-Dist: bumpversion ; extra == 'dev'
Requires-Dist: wheel ; extra == 'dev'
Requires-Dist: black (==20.8b1) ; extra == 'dev'
Requires-Dist: setuptools-golang ; extra == 'dev'
Provides-Extra: tests
Requires-Dist: psutil ; extra == 'tests'
Requires-Dist: pytest ; extra == 'tests'
Requires-Dist: boto3 ; extra == 'tests'
